bit8tools/__init__.py
bit8tools/alignment.py
bit8tools/colors.py
bit8tools/input.py
bit8tools/output.py
bit8tools/py.typed
bit8tools/tabular.py
bit8tools-1.0.8.dist-info/METADATA
bit8tools-1.0.8.dist-info/WHEEL
bit8tools-1.0.8.dist-info/top_level.txt
bit8tools-1.0.8.dist-info/RECORD
