Metadata-Version: 2.2
Name: bit8tools
Version: 1.0.8
Summary: Una librería para mejorar la interacción en la consola
Author-email: Agustín Comolli <agustincomolli@gmail.com>
License: MIT License
Classifier: Programming Language :: Python :: 3
Classifier: License :: OSI Approved :: MIT License
Classifier: Operating System :: OS Independent
Requires-Python: >=3.6
